AC2/labs/lab2/full_adder.sv
module full_adder (
    input logic x_i,
    input logic y_i,
    input logic c_i,

    output logic s_o,
    output logic c_o
);
    // Internal variables
    logic a_int;
    logic b_int;
    logic d_int;

    // Compute internal variables
    assign #100 a_int = x_i ^ y_i;
    assign #50 b_int = c_i & a_int;
    assign #50 d_int = x_i & y_i;

    // Compute the result
    assign #100 s_o = a_int ^ c_i;
    assign #100 c_o = b_int | d_int;

endmodule;

AC2/labs/lab2/adder_4bits.sv
module adder_4bits (
	input logic [3:0] x_i,
	input logic [3:0] y_i,
	input logic c_i,
	output logic [3:0] s_o,
	output logic c_o
);

	logic [4:0] adder;
	genvar i;
	assign adder[0] = c_i;
	assign c_o = adder[4];
generate
	for (i = 0; i < 4; ++i) begin
		full_adder almendras(
			.x_i(x_i[i]),
			.y_i(y_i[i]), 
			.c_i(adder[i]), 
			.s_o(s_o[i]),
			.c_o(adder[i+1]) 
		);
	end
endgenerate
endmodule

AC2/labs/lab2/tb_adder_4bits.sv
module tb_adder_4bits;

    // Signal declaration
    parameter WIDTH = 4;
    parameter TESTSUM = 16;
    logic [WIDTH-1:0] x, y, s;
    logic [WIDTH:0] tmp;
    logic c_in, c_out;
    logic clk;
    integer i, j;

    initial begin
        
    end

    // Instance of the adder_4bits under test
    adder_4bits adder (
      .x_i(x),
      .y_i(y),
      .c_i(c_in),
      .s_o(s),
      .c_o(c_out)
    );

    // Basic test for all the input combinations
    task basic_functional_testing();
        $display(" ------------------------------------------------");
        $display(" Basic test ");
        $display(" ------------------------------------------------");

        clk = 1; x = 0; y = 0; c_in = 0;
        #500 clk = 0;
        #500
        for (i = 0; i < TESTSUM; i++) begin
            for (j = 0; j < TESTSUM; j++) begin
                clk = 1;
                x = i[WIDTH-1:0];
                y = j[WIDTH-1:0];
                #500 clk = 0;
                tmp = x + y;
                #500 assert ((s[WIDTH-1:0] == (i[WIDTH-1:0]+j[WIDTH-1:0])) &&
                             (c_out == tmp[WIDTH]))
                     $display("(%0d) x=%d y=%d Cin=%b -> Sum=%d Cout=%b\n",$time,x,y,c_in,s,c_out);
                     else $error("ERROR! (%0d) x=%d y=%d Cin=%b -> Sum=%d Cout=%b\n",$time,x,y,c_in,s,c_out);
            end
        end
    endtask

    // Transition test for evaluating the different delays
    task transition_test(
        input logic [WIDTH-1:0] a0,
        input logic [WIDTH-1:0] b0,
        input logic 			c0,
        input logic [WIDTH-1:0] a1,
        input logic [WIDTH-1:0] b1,
        input logic 			c1);

        $display(" ------------------------------------------------");
        $display(" Transition test: x=%b->%b y=%b->%b Cin=%b->%b",a0,a1,b0,b1,c0,c1);
        $display(" ------------------------------------------------");


        clk = 1; x = a0; y = b0; c_in = c0;
        #500 clk = 0;
        #500 $display("(%0d) FROM: x=%b y=%b Cin=%b -> Sum=%b Cout=%b\n",$time,x,y,c_in,s,c_out);
        clk = 1; x = a1; y = b1; c_in = c1;
        #500 clk = 0;
        #500 $display("(%0d) TO: x=%b y=%b Cin=%b -> Sum=%b Cout=%b\n",$time,x,y,c_in,s,c_out);
    endtask

    // Main execution flow of the testbench
    initial begin 
        // wavefrom generation
        $dumpfile("waveform.vcd");
        $dumpvars();

        // Functionality testing of the 
        basic_functional_testing();
        transition_test(    
            4'b0000,4'b0000,1'b0,  // from (x,y,c)
            4'b0001,4'b0001,1'b1); // to   (x,y,c)
        $finish();
    end
                 
endmodule

AC2/labs/lab2/waveform.vcd
$version Generated by VerilatedVcd $end
$timescale 1ps $end
 $scope module TOP $end
  $scope module tb_adder_4bits $end
   $var wire 32 H WIDTH [31:0] $end
   $var wire 32 I TESTSUM [31:0] $end
   $var wire 4 # x [3:0] $end
   $var wire 4 $ y [3:0] $end
   $var wire 4 2 s [3:0] $end
   $var wire 5 % tmp [4:0] $end
   $var wire 1 & c_in $end
   $var wire 1 3 c_out $end
   $var wire 1 ' clk $end
   $var wire 32 ( i [31:0] $end
   $var wire 32 ) j [31:0] $end
   $scope module adder $end
    $var wire 4 # x_i [3:0] $end
    $var wire 4 $ y_i [3:0] $end
    $var wire 1 & c_i $end
    $var wire 4 2 s_o [3:0] $end
    $var wire 1 3 c_o $end
    $var wire 5 G adder [4:0] $end
    $scope module genblk1[0] $end
     $scope module almendras $end
      $var wire 1 * x_i $end
      $var wire 1 + y_i $end
      $var wire 1 & c_i $end
      $var wire 1 4 s_o $end
      $var wire 1 5 c_o $end
      $var wire 1 6 a_int $end
      $var wire 1 7 b_int $end
      $var wire 1 8 d_int $end
     $upscope $end
    $upscope $end
    $scope module genblk1[1] $end
     $scope module almendras $end
      $var wire 1 , x_i $end
      $var wire 1 - y_i $end
      $var wire 1 5 c_i $end
      $var wire 1 9 s_o $end
      $var wire 1 : c_o $end
      $var wire 1 ; a_int $end
      $var wire 1 < b_int $end
      $var wire 1 = d_int $end
     $upscope $end
    $upscope $end
    $scope module genblk1[2] $end
     $scope module almendras $end
      $var wire 1 . x_i $end
      $var wire 1 / y_i $end
      $var wire 1 : c_i $end
      $var wire 1 > s_o $end
      $var wire 1 ? c_o $end
      $var wire 1 @ a_int $end
      $var wire 1 A b_int $end
      $var wire 1 B d_int $end
     $upscope $end
    $upscope $end
    $scope module genblk1[3] $end
     $scope module almendras $end
      $var wire 1 0 x_i $end
      $var wire 1 1 y_i $end
      $var wire 1 ? c_i $end
      $var wire 1 C s_o $end
      $var wire 1 3 c_o $end
      $var wire 1 D a_int $end
      $var wire 1 E b_int $end
      $var wire 1 F d_int $end
     $upscope $end
    $upscope $end
   $upscope $end
  $upscope $end
 $upscope $end
$enddefinitions $end


#0
b0000 #
b0000 $
b00000 %
0&
1'
b00000000000000000000000000000000 (
b00000000000000000000000000000000 )
0*
0+
0,
0-
0.
0/
00
01
b0000 2
03
04
05
06
07
08
09
0:
0;
0<
0=
0>
0?
0@
0A
0B
0C
0D
0E
0F
b00000 G
b00000000000000000000000000000100 H
b00000000000000000000000000010000 I
#50
#100
#150
#200
#250
#300
#350
#400
#450
#500
0'
#550
#600
#650
#700
#750
#800
#850
#900
#950
#1000
1'
#1050
#1100
#1150
#1200
#1250
#1300
#1350
#1400
#1450
#1500
0'
#1550
#1600
#1650
#1700
#1750
#1800
#1850
#1900
#1950
#2000
b0001 $
1'
b00000000000000000000000000000001 )
1+
#2050
#2100
16
#2150
#2200
b0001 2
14
#2250
#2300
#2350
#2400
#2450
#2500
b00001 %
0'
#2550
#2600
#2650
#2700
#2750
#2800
#2850
#2900
#2950
#3000
b0010 $
1'
b00000000000000000000000000000010 )
0+
1-
#3050
#3100
06
1;
#3150
#3200
b0010 2
04
19
#3250
#3300
#3350
#3400
#3450
#3500
b00010 %
0'
#3550
#3600
#3650
#3700
#3750
#3800
#3850
#3900
#3950
#4000
b0011 $
1'
b00000000000000000000000000000011 )
1+
#4050
#4100
16
#4150
#4200
b0011 2
14
#4250
#4300
#4350
#4400
#4450
#4500
b00011 %
0'
#4550
#4600
#4650
#4700
#4750
#4800
#4850
#4900
#4950
#5000
b0100 $
1'
b00000000000000000000000000000100 )
0+
0-
1/
#5050
#5100
06
0;
1@
#5150
#5200
b0100 2
04
09
1>
#5250
#5300
#5350
#5400
#5450
#5500
b00100 %
0'
#5550
#5600
#5650
#5700
#5750
#5800
#5850
#5900
#5950
#6000
b0101 $
1'
b00000000000000000000000000000101 )
1+
#6050
#6100
16
#6150
#6200
b0101 2
14
#6250
#6300
#6350
#6400
#6450
#6500
b00101 %
0'
#6550
#6600
#6650
#6700
#6750
#6800
#6850
#6900
#6950
#7000
b0110 $
1'
b00000000000000000000000000000110 )
0+
1-
#7050
#7100
06
1;
#7150
#7200
b0110 2
04
19
#7250
#7300
#7350
#7400
#7450
#7500
b00110 %
0'
#7550
#7600
#7650
#7700
#7750
#7800
#7850
#7900
#7950
#8000
b0111 $
1'
b00000000000000000000000000000111 )
1+
#8050
#8100
16
#8150
#8200
b0111 2
14
#8250
#8300
#8350
#8400
#8450
#8500
b00111 %
0'
#8550
#8600
#8650
#8700
#8750
#8800
#8850
#8900
#8950
#9000
b1000 $
1'
b00000000000000000000000000001000 )
0+
0-
0/
11
#9050
#9100
06
0;
0@
1D
#9150
#9200
b1000 2
04
09
0>
1C
#9250
#9300
#9350
#9400
#9450
#9500
b01000 %
0'
#9550
#9600
#9650
#9700
#9750
#9800
#9850
#9900
#9950
#10000
b1001 $
1'
b00000000000000000000000000001001 )
1+
#10050
#10100
16
#10150
#10200
b1001 2
14
#10250
#10300
#10350
#10400
#10450
#10500
b01001 %
0'
#10550
#10600
#10650
#10700
#10750
#10800
#10850
#10900
#10950
#11000
b1010 $
1'
b00000000000000000000000000001010 )
0+
1-
#11050
#11100
06
1;
#11150
#11200
b1010 2
04
19
#11250
#11300
#11350
#11400
#11450
#11500
b01010 %
0'
#11550
#11600
#11650
#11700
#11750
#11800
#11850
#11900
#11950
#12000
b1011 $
1'
b00000000000000000000000000001011 )
1+
#12050
#12100
16
#12150
#12200
b1011 2
14
#12250
#12300
#12350
#12400
#12450
#12500
b01011 %
0'
#12550
#12600
#12650
#12700
#12750
#12800
#12850
#12900
#12950
#13000
b1100 $
1'
b00000000000000000000000000001100 )
0+
0-
1/
#13050
#13100
06
0;
1@
#13150
#13200
b1100 2
04
09
1>
#13250
#13300
#13350
#13400
#13450
#13500
b01100 %
0'
#13550
#13600
#13650
#13700
#13750
#13800
#13850
#13900
#13950
#14000
b1101 $
1'
b00000000000000000000000000001101 )
1+
#14050
#14100
16
#14150
#14200
b1101 2
14
#14250
#14300
#14350
#14400
#14450
#14500
b01101 %
0'
#14550
#14600
#14650
#14700
#14750
#14800
#14850
#14900
#14950
#15000
b1110 $
1'
b00000000000000000000000000001110 )
0+
1-
#15050
#15100
06
1;
#15150
#15200
b1110 2
04
19
#15250
#15300
#15350
#15400
#15450
#15500
b01110 %
0'
#15550
#15600
#15650
#15700
#15750
#15800
#15850
#15900
#15950
#16000
b1111 $
1'
b00000000000000000000000000001111 )
1+
#16050
#16100
16
#16150
#16200
b1111 2
14
#16250
#16300
#16350
#16400
#16450
#16500
b01111 %
0'
#16550
#16600
#16650
#16700
#16750
#16800
#16850
#16900
#16950
#17000
b0001 #
b0000 $
1'
b00000000000000000000000000000001 (
b00000000000000000000000000010000 )
1*
0+
0-
0/
01
#17050
#17100
0;
0@
0D
#17150
#17200
b0001 2
09
0>
0C
#17250
#17300
#17350
#17400
#17450
#17500
b00001 %
0'
#17550
#17600
#17650
#17700
#17750
#17800
#17850
#17900
#17950
#18000
b0001 $
1'
b00000000000000000000000000000001 )
1+
#18050
18
#18100
06
#18150
15
b00010 G
#18200
b0000 2
04
#18250
b0010 2
19
#18300
#18350
#18400
#18450
#18500
b00010 %
0'
#18550
#18600
#18650
#18700
#18750
#18800
#18850
#18900
#18950
#19000
b0010 $
1'
b00000000000000000000000000000010 )
0+
1-
#19050
08
#19100
16
1;
#19150
05
1<
b00000 G
#19200
b0001 2
14
09
0<
#19250
b0011 2
19
1:
b00100 G
#19300
0:
b00000 G
#19350
b0111 2
1>
#19400
b0011 2
0>
#19450
#19500
b00011 %
0'
#19550
#19600
#19650
#19700
#19750
#19800
#19850
#19900
#19950
#20000
b0011 $
1'
b00000000000000000000000000000011 )
1+
#20050
18
#20100
06
#20150
15
b00010 G
#20200
b0010 2
04
1<
#20250
b0000 2
09
#20300
1:
b00110 G
#20350
#20400
b0100 2
1>
#20450
#20500
b00100 %
0'
#20550
#20600
#20650
#20700
#20750
#20800
#20850
#20900
#20950
#21000
b0100 $
1'
b00000000000000000000000000000100 )
0+
0-
1/
#21050
08
#21100
16
0;
1@
#21150
05
0<
1A
b00100 G
#21200
b0011 2
14
19
0>
#21250
b0001 2
09
0:
1?
b01000 G
#21300
0A
#21350
b1101 2
1>
1C
#21400
0?
b00000 G
#21450
#21500
b00101 %
0'
b0101 2
0C
#21550
#21600
#21650
#21700
#21750
#21800
#21850
#21900
#21950
#22000
b0101 $
1'
b00000000000000000000000000000101 )
1+
#22050
18
#22100
06
#22150
15
b00010 G
#22200
b0100 2
04
#22250
b0110 2
19
#22300
#22350
#22400
#22450
#22500
b00110 %
0'
#22550
#22600
#22650
#22700
#22750
#22800
#22850
#22900
#22950
#23000
b0110 $
1'
b00000000000000000000000000000110 )
0+
1-
#23050
08
#23100
16
1;
#23150
05
1<
b00000 G
#23200
b0101 2
14
09
0<
#23250
b0111 2
19
1:
b00100 G
#23300
0:
1A
b00000 G
#23350
b0011 2
0>
0A
#23400
b0111 2
1>
1?
b01000 G
#23450
0?
b00000 G
#23500
b00111 %
0'
b1111 2
1C
#23550
b0111 2
0C
#23600
#23650
#23700
#23750
#23800
#23850
#23900
#23950
#24000
b0111 $
1'
b00000000000000000000000000000111 )
1+
#24050
18
#24100
06
#24150
15
b00010 G
#24200
b0110 2
04
1<
#24250
b0100 2
09
#24300
1:
b00110 G
#24350
1A
#24400
b0000 2
0>
#24450
1?
b01110 G
#24500
b01000 %
0'
#24550
b1000 2
1C
#24600
#24650
#24700
#24750
#24800
#24850
#24900
#24950
#25000
b1000 $
1'
b00000000000000000000000000001000 )
0+
0-
0/
11
#25050
08
#25100
16
0;
0@
1D
#25150
05
0<
0A
1E
b01100 G
#25200
b0111 2
14
19
1>
0C
#25250
b0101 2
13
09
0:
0?
b10000 G
#25300
0E
#25350
b1001 2
0>
1C
#25400
03
b00000 G
#25450
#25500
b01001 %
0'
#25550
#25600
#25650
#25700
#25750
#25800
#25850
#25900
#25950
#26000
b1001 $
1'
b00000000000000000000000000001001 )
1+
#26050
18
#26100
06
#26150
15
b00010 G
#26200
b1000 2
04
#26250
b1010 2
19
#26300
#26350
#26400
#26450
#26500
b01010 %
0'
#26550
#26600
#26650
#26700
#26750
#26800
#26850
#26900
#26950
#27000
b1010 $
1'
b00000000000000000000000000001010 )
0+
1-
#27050
08
#27100
16
1;
#27150
05
1<
b00000 G
#27200
b1001 2
14
09
0<
#27250
b1011 2
19
1:
b00100 G
#27300
0:
b00000 G
#27350
b1111 2
1>
#27400
b1011 2
0>
#27450
#27500
b01011 %
0'
#27550
#27600
#27650
#27700
#27750
#27800
#27850
#27900
#27950
#28000
b1011 $
1'
b00000000000000000000000000001011 )
1+
#28050
18
#28100
06
#28150
15
b00010 G
#28200
b1010 2
04
1<
#28250
b1000 2
09
#28300
1:
b00110 G
#28350
#28400
b1100 2
1>
#28450
#28500
b01100 %
0'
#28550
#28600
#28650
#28700
#28750
#28800
#28850
#28900
#28950
#29000
b1100 $
1'
b00000000000000000000000000001100 )
0+
0-
1/
#29050
08
#29100
16
0;
1@
#29150
05
0<
1A
b00100 G
#29200
b1011 2
14
19
0>
#29250
b1001 2
09
0:
1?
b01000 G
#29300
0A
1E
#29350
b0101 2
1>
0C
#29400
13
0?
b10000 G
#29450
0E
#29500
b01101 %
0'
b1101 2
1C
#29550
03
b00000 G
#29600
#29650
#29700
#29750
#29800
#29850
#29900
#29950
#30000
b1101 $
1'
b00000000000000000000000000001101 )
1+
#30050
18
#30100
06
#30150
15
b00010 G
#30200
b1100 2
04
#30250
b1110 2
19
#30300
#30350
#30400
#30450
#30500
b01110 %
0'
#30550
#30600
#30650
#30700
#30750
#30800
#30850
#30900
#30950
#31000
b1110 $
1'
b00000000000000000000000000001110 )
0+
1-
#31050
08
#31100
16
1;
#31150
05
1<
b00000 G
#31200
b1101 2
14
09
0<
#31250
b1111 2
19
1:
b00100 G
#31300
0:
1A
b00000 G
#31350
b1011 2
0>
0A
#31400
b1111 2
1>
1?
b01000 G
#31450
0?
1E
b00000 G
#31500
b01111 %
0'
b0111 2
0C
0E
#31550
b1111 2
13
1C
b10000 G
#31600
03
b00000 G
#31650
#31700
#31750
#31800
#31850
#31900
#31950
#32000
b1111 $
1'
b00000000000000000000000000001111 )
1+
#32050
18
#32100
06
#32150
15
b00010 G
#32200
b1110 2
04
1<
#32250
b1100 2
09
#32300
1:
b00110 G
#32350
1A
#32400
b1000 2
0>
#32450
1?
b01110 G
#32500
b10000 %
0'
1E
#32550
b0000 2
0C
#32600
13
b11110 G
#32650
#32700
#32750
#32800
#32850
#32900
#32950
#33000
b0010 #
b0000 $
1'
b00000000000000000000000000000010 (
b00000000000000000000000000010000 )
0*
0+
1,
0-
0/
01
#33050
08
#33100
0@
0D
#33150
05
0A
0E
b11100 G
#33200
b1100 2
0<
1>
1C
#33250
b1110 2
03
19
0?
b00100 G
#33300
0:
b00000 G
#33350
b0110 2
0C
#33400
b0010 2
0>
#33450
#33500
b00010 %
0'
#33550
#33600
#33650
#33700
#33750
#33800
#33850
#33900
#33950
#34000
b0001 $
1'
b00000000000000000000000000000001 )
1+
#34050
#34100
16
#34150
#34200
b0011 2
14
#34250
#34300
#34350
#34400
#34450
#34500
b00011 %
0'
#34550
#34600
#34650
#34700
#34750
#34800
#34850
#34900
#34950
#35000
b0010 $
1'
b00000000000000000000000000000010 )
0+
1-
#35050
1=
#35100
06
0;
#35150
1:
b00100 G
#35200
b0000 2
04
09
#35250
b0100 2
1>
#35300
#35350
#35400
#35450
#35500
b00100 %
0'
#35550
#35600
#35650
#35700
#35750
#35800
#35850
#35900
#35950
#36000
b0011 $
1'
b00000000000000000000000000000011 )
1+
#36050
#36100
16
#36150
#36200
b0101 2
14
#36250
#36300
#36350
#36400
#36450
#36500
b00101 %
0'
#36550
#36600
#36650
#36700
#36750
#36800
#36850
#36900
#36950
#37000
b0100 $
1'
b00000000000000000000000000000100 )
0+
0-
1/
#37050
0=
#37100
06
1;
1@
#37150
0:
1A
b00000 G
#37200
b0010 2
04
19
0>
0A
#37250
b0110 2
1>
1?
b01000 G
#37300
0?
b00000 G
#37350
b1110 2
1C
#37400
b0110 2
0C
#37450
#37500
b00110 %
0'
#37550
#37600
#37650
#37700
#37750
#37800
#37850
#37900
#37950
#38000
b0101 $
1'
b00000000000000000000000000000101 )
1+
#38050
#38100
16
#38150
#38200
b0111 2
14
#38250
#38300
#38350
#38400
#38450
#38500
b00111 %
0'
#38550
#38600
#38650
#38700
#38750
#38800
#38850
#38900
#38950
#39000
b0110 $
1'
b00000000000000000000000000000110 )
0+
1-
#39050
1=
#39100
06
0;
#39150
1:
b00100 G
#39200
b0100 2
04
09
1A
#39250
b0000 2
0>
#39300
1?
b01100 G
#39350
#39400
b1000 2
1C
#39450
#39500
b01000 %
0'
#39550
#39600
#39650
#39700
#39750
#39800
#39850
#39900
#39950
#40000
b0111 $
1'
b00000000000000000000000000000111 )
1+
#40050
#40100
16
#40150
#40200
b1001 2
14
#40250
#40300
#40350
#40400
#40450
#40500
b01001 %
0'
#40550
#40600
#40650
#40700
#40750
#40800
#40850
#40900
#40950
#41000
b1000 $
1'
b00000000000000000000000000001000 )
0+
0-
0/
11
#41050
0=
#41100
06
1;
0@
1D
#41150
0:
0A
1E
b01000 G
#41200
b0110 2
04
19
1>
0C
#41250
b0010 2
13
0>
0?
b10000 G
#41300
0E
#41350
b1010 2
1C
#41400
03
b00000 G
#41450
#41500
b01010 %
0'
#41550
#41600
#41650
#41700
#41750
#41800
#41850
#41900
#41950
#42000
b1001 $
1'
b00000000000000000000000000001001 )
1+
#42050
#42100
16
#42150
#42200
b1011 2
14
#42250
#42300
#42350
#42400
#42450
#42500
b01011 %
0'
#42550
#42600
#42650
#42700
#42750
#42800
#42850
#42900
#42950
#43000
b1010 $
1'
b00000000000000000000000000001010 )
0+
1-
#43050
1=
#43100
06
0;
#43150
1:
b00100 G
#43200
b1000 2
04
09
#43250
b1100 2
1>
#43300
#43350
#43400
#43450
#43500
b01100 %
0'
#43550
#43600
#43650
#43700
#43750
#43800
#43850
#43900
#43950
#44000
b1011 $
1'
b00000000000000000000000000001011 )
1+
#44050
#44100
16
#44150
#44200
b1101 2
14
#44250
#44300
#44350
#44400
#44450
#44500
b01101 %
0'
#44550
#44600
#44650
#44700
#44750
#44800
#44850
#44900
#44950
#45000
b1100 $
1'
b00000000000000000000000000001100 )
0+
0-
1/
#45050
0=
#45100
06
1;
1@
#45150
0:
1A
b00000 G
#45200
b1010 2
04
19
0>
0A
#45250
b1110 2
1>
1?
b01000 G
#45300
0?
1E
b00000 G
#45350
b0110 2
0C
0E
#45400
b1110 2
13
1C
b10000 G
#45450
03
b00000 G
#45500
b01110 %
0'
#45550
#45600
#45650
#45700
#45750
#45800
#45850
#45900
#45950
#46000
b1101 $
1'
b00000000000000000000000000001101 )
1+
#46050
#46100
16
#46150
#46200
b1111 2
14
#46250
#46300
#46350
#46400
#46450
#46500
b01111 %
0'
#46550
#46600
#46650
#46700
#46750
#46800
#46850
#46900
#46950
#47000
b1110 $
1'
b00000000000000000000000000001110 )
0+
1-
#47050
1=
#47100
06
0;
#47150
1:
b00100 G
#47200
b1100 2
04
09
1A
#47250
b1000 2
0>
#47300
1?
b01100 G
#47350
1E
#47400
b0000 2
0C
#47450
13
b11100 G
#47500
b10000 %
0'
#47550
#47600
#47650
#47700
#47750
#47800
#47850
#47900
#47950
#48000
b1111 $
1'
b00000000000000000000000000001111 )
1+
#48050
#48100
16
#48150
#48200
b0001 2
14
#48250
#48300
#48350
#48400
#48450
#48500
b10001 %
0'
#48550
#48600
#48650
#48700
#48750
#48800
#48850
#48900
#48950
#49000
b0011 #
b0000 $
1'
b00000000000000000000000000000011 (
b00000000000000000000000000010000 )
1*
0+
0-
0/
01
#49050
0=
#49100
1;
0@
0D
#49150
0:
0A
0E
b11000 G
#49200
b1111 2
19
1>
1C
#49250
b1011 2
03
0>
0?
b00000 G
#49300
#49350
b0011 2
0C
#49400
#49450
#49500
b00011 %
0'
#49550
#49600
#49650
#49700
#49750
#49800
#49850
#49900
#49950
#50000
b0001 $
1'
b00000000000000000000000000000001 )
1+
#50050
18
#50100
06
#50150
15
b00010 G
#50200
b0010 2
04
1<
#50250
b0000 2
09
#50300
1:
b00110 G
#50350
#50400
b0100 2
1>
#50450
#50500
b00100 %
0'
#50550
#50600
#50650
#50700
#50750
#50800
#50850
#50900
#50950
#51000
b0010 $
1'
b00000000000000000000000000000010 )
0+
1-
#51050
08
1=
#51100
16
0;
#51150
05
0<
b00100 G
#51200
b0111 2
14
19
#51250
b0101 2
09
#51300
#51350
#51400
#51450
#51500
b00101 %
0'
#51550
#51600
#51650
#51700
#51750
#51800
#51850
#51900
#51950
#52000
b0011 $
1'
b00000000000000000000000000000011 )
1+
#52050
18
#52100
06
#52150
15
b00110 G
#52200
b0100 2
04
#52250
b0110 2
19
#52300
#52350
#52400
#52450
#52500
b00110 %
0'
#52550
#52600
#52650
#52700
#52750
#52800
#52850
#52900
#52950
#53000
b0100 $
1'
b00000000000000000000000000000100 )
0+
0-
1/
#53050
08
0=
#53100
16
1;
1@
#53150
05
0:
1<
1A
b00000 G
#53200
b0001 2
14
09
0<
0>
0A
#53250
b0111 2
19
1:
1>
1?
b01100 G
#53300
0:
0?
1A
b00000 G
#53350
b1011 2
0>
0A
1C
#53400
b0111 2
1>
1?
0C
b01000 G
#53450
0?
b00000 G
#53500
b00111 %
0'
b1111 2
1C
#53550
b0111 2
0C
#53600
#53650
#53700
#53750
#53800
#53850
#53900
#53950
#54000
b0101 $
1'
b00000000000000000000000000000101 )
1+
#54050
18
#54100
06
#54150
15
b00010 G
#54200
b0110 2
04
1<
#54250
b0100 2
09
#54300
1:
b00110 G
#54350
1A
#54400
b0000 2
0>
#54450
1?
b01110 G
#54500
b01000 %
0'
#54550
b1000 2
1C
#54600
#54650
#54700
#54750
#54800
#54850
#54900
#54950
#55000
b0110 $
1'
b00000000000000000000000000000110 )
0+
1-
#55050
08
1=
#55100
16
0;
#55150
05
0<
b01100 G
#55200
b1011 2
14
19
#55250
b1001 2
09
#55300
#55350
#55400
#55450
#55500
b01001 %
0'
#55550
#55600
#55650
#55700
#55750
#55800
#55850
#55900
#55950
#56000
b0111 $
1'
b00000000000000000000000000000111 )
1+
#56050
18
#56100
06
#56150
15
b01110 G
#56200
b1000 2
04
#56250
b1010 2
19
#56300
#56350
#56400
#56450
#56500
b01010 %
0'
#56550
#56600
#56650
#56700
#56750
#56800
#56850
#56900
#56950
#57000
b1000 $
1'
b00000000000000000000000000001000 )
0+
0-
0/
11
#57050
08
0=
#57100
16
1;
0@
1D
#57150
05
0:
1<
0A
1E
b01000 G
#57200
b0101 2
14
09
0<
1>
0C
#57250
b0011 2
13
19
1:
0>
0?
b10100 G
#57300
0:
0E
b10000 G
#57350
b1111 2
1>
1C
#57400
b1011 2
03
0>
b00000 G
#57450
#57500
b01011 %
0'
#57550
#57600
#57650
#57700
#57750
#57800
#57850
#57900
#57950
#58000
b1001 $
1'
b00000000000000000000000000001001 )
1+
#58050
18
#58100
06
#58150
15
b00010 G
#58200
b1010 2
04
1<
#58250
b1000 2
09
#58300
1:
b00110 G
#58350
#58400
b1100 2
1>
#58450
#58500
b01100 %
0'
#58550
#58600
#58650
#58700
#58750
#58800
#58850
#58900
#58950
#59000
b1010 $
1'
b00000000000000000000000000001010 )
0+
1-
#59050
08
1=
#59100
16
0;
#59150
05
0<
b00100 G
#59200
b1111 2
14
19
#59250
b1101 2
09
#59300
#59350
#59400
#59450
#59500
b01101 %
0'
#59550
#59600
#59650
#59700
#59750
#59800
#59850
#59900
#59950
#60000
b1011 $
1'
b00000000000000000000000000001011 )
1+
#60050
18
#60100
06
#60150
15
b00110 G
#60200
b1100 2
04
#60250
b1110 2
19
#60300
#60350
#60400
#60450
#60500
b01110 %
0'
#60550
#60600
#60650
#60700
#60750
#60800
#60850
#60900
#60950
#61000
b1100 $
1'
b00000000000000000000000000001100 )
0+
0-
1/
#61050
08
0=
#61100
16
1;
1@
#61150
05
0:
1<
1A
b00000 G
#61200
b1001 2
14
09
0<
0>
0A
#61250
b1111 2
19
1:
1>
1?
b01100 G
#61300
0:
0?
1A
1E
b00000 G
#61350
b0011 2
0>
0A
0C
0E
#61400
b1111 2
13
1>
1?
1C
b11000 G
#61450
03
0?
1E
b00000 G
#61500
b01111 %
0'
b0111 2
0C
0E
#61550
b1111 2
13
1C
b10000 G
#61600
03
b00000 G
#61650
#61700
#61750
#61800
#61850
#61900
#61950
#62000
b1101 $
1'
b00000000000000000000000000001101 )
1+
#62050
18
#62100
06
#62150
15
b00010 G
#62200
b1110 2
04
1<
#62250
b1100 2
09
#62300
1:
b00110 G
#62350
1A
#62400
b1000 2
0>
#62450
1?
b01110 G
#62500
b10000 %
0'
1E
#62550
b0000 2
0C
#62600
13
b11110 G
#62650
#62700
#62750
#62800
#62850
#62900
#62950
#63000
b1110 $
1'
b00000000000000000000000000001110 )
0+
1-
#63050
08
1=
#63100
16
0;
#63150
05
0<
b11100 G
#63200
b0011 2
14
19
#63250
b0001 2
09
#63300
#63350
#63400
#63450
#63500
b10001 %
0'
#63550
#63600
#63650
#63700
#63750
#63800
#63850
#63900
#63950
#64000
b1111 $
1'
b00000000000000000000000000001111 )
1+
#64050
18
#64100
06
#64150
15
b11110 G
#64200
b0000 2
04
#64250
b0010 2
19
#64300
#64350
#64400
#64450
#64500
b10010 %
0'
#64550
#64600
#64650
#64700
#64750
#64800
#64850
#64900
#64950
#65000
b0100 #
b0000 $
1'
b00000000000000000000000000000100 (
b00000000000000000000000000010000 )
0*
0+
0,
0-
1.
0/
01
#65050
08
0=
#65100
0D
#65150
05
0:
0E
b11000 G
#65200
b1010 2
0A
1C
#65250
b1100 2
03
09
1>
b01000 G
#65300
0?
b00000 G
#65350
#65400
b0100 2
0C
#65450
#65500
b00100 %
0'
#65550
#65600
#65650
#65700
#65750
#65800
#65850
#65900
#65950
#66000
b0001 $
1'
b00000000000000000000000000000001 )
1+
#66050
#66100
16
#66150
#66200
b0101 2
14
#66250
#66300
#66350
#66400
#66450
#66500
b00101 %
0'
#66550
#66600
#66650
#66700
#66750
#66800
#66850
#66900
#66950
#67000
b0010 $
1'
b00000000000000000000000000000010 )
0+
1-
#67050
#67100
06
1;
#67150
#67200
b0110 2
04
19
#67250
#67300
#67350
#67400
#67450
#67500
b00110 %
0'
#67550
#67600
#67650
#67700
#67750
#67800
#67850
#67900
#67950
#68000
b0011 $
1'
b00000000000000000000000000000011 )
1+
#68050
#68100
16
#68150
#68200
b0111 2
14
#68250
#68300
#68350
#68400
#68450
#68500
b00111 %
0'
#68550
#68600
#68650
#68700
#68750
#68800
#68850
#68900
#68950
#69000
b0100 $
1'
b00000000000000000000000000000100 )
0+
0-
1/
#69050
1B
#69100
06
0;
0@
#69150
1?
b01000 G
#69200
b0000 2
04
09
0>
#69250
b1000 2
1C
#69300
#69350
#69400
#69450
#69500
b01000 %
0'
#69550
#69600
#69650
#69700
#69750
#69800
#69850
#69900
#69950
#70000
b0101 $
1'
b00000000000000000000000000000101 )
1+
#70050
#70100
16
#70150
#70200
b1001 2
14
#70250
#70300
#70350
#70400
#70450
#70500
b01001 %
0'
#70550
#70600
#70650
#70700
#70750
#70800
#70850
#70900
#70950
#71000
b0110 $
1'
b00000000000000000000000000000110 )
0+
1-
#71050
#71100
06
1;
#71150
#71200
b1010 2
04
19
#71250
#71300
#71350
#71400
#71450
#71500
b01010 %
0'
#71550
#71600
#71650
#71700
#71750
#71800
#71850
#71900
#71950
#72000
b0111 $
1'
b00000000000000000000000000000111 )
1+
#72050
#72100
16
#72150
#72200
b1011 2
14
#72250
#72300
#72350
#72400
#72450
#72500
b01011 %
0'
#72550
#72600
#72650
#72700
#72750
#72800
#72850
#72900
#72950
#73000
b1000 $
1'
b00000000000000000000000000001000 )
0+
0-
0/
11
#73050
0B
#73100
06
0;
1@
1D
#73150
0?
1E
b00000 G
#73200
b0100 2
04
09
1>
0C
0E
#73250
b1100 2
13
1C
b10000 G
#73300
03
b00000 G
#73350
#73400
#73450
#73500
b01100 %
0'
#73550
#73600
#73650
#73700
#73750
#73800
#73850
#73900
#73950
