AC2/labs/lab2/full_adder.sv
module full_adder (
    input logic x_i,
    input logic y_i,
    input logic c_i,

    output logic s_o,
    output logic c_o
);
    // Internal variables
    logic a_int;
    logic b_int;
    logic d_int;

    // Compute internal variables
    assign #100 a_int = x_i ^ y_i;
    assign #50 b_int = c_i & a_int;
    assign #50 d_int = x_i & y_i;

    // Compute the result
    assign #100 s_o = a_int ^ c_i;
    assign #100 c_o = b_int | d_int;

endmodule;

AC2/labs/lab2/adder_nbits.sv
module adder_nbits #(parameter WIDTH) (
	input logic [WIDTH-1:0] x_i,
	input logic [WIDTH-1:0] y_i,
	input logic c_i,
	output logic [WIDTH-1:0] s_o,
	output logic c_o
);

	logic [WIDTH:0] adder;
	genvar i;
	assign adder[0] = c_i;
	assign c_o = adder[WIDTH];
generate
	for (i = 0; i < WIDTH; ++i) begin
		full_adder almendras2(
			.x_i(x_i[i]),
			.y_i(y_i[i]), 
			.c_i(adder[i]), 
			.s_o(s_o[i]),
			.c_o(adder[i+1]) 
		);
	end
endgenerate
endmodule

AC2/labs/lab2/accum_nbits.sv
module accum_nbits #(parameter WIDTH = 32) (
	input logic clk_i, // clock del registro
	input logic nrst_i, // boton de reset?
	input logic [WIDTH-1:0] x_i, // input 
	output logic [WIDTH-1:0] y_o // y_o de i se guarda en el registro, t_o de i+1 se suma a x_i
);

	logic [WIDTH-1:0] aux;
	
	adder_nbits #(.WIDTH(WIDTH)) almendras3( 
		.x_i(x_i),
		.y_i(aux), // registro, inicialmente 0 
		.c_i(1'b0), // NO SE, POR AHORA LO GUARDO O ALGO
		.s_o(y_o), // AL REGISTRO
		.c_o() // IGUAL NO SE
	);

	always_ff@(posedge clk_i, nrst_i) begin //Revisar si lo queremos en el flanco ascendente o descendente
		if (~nrst_i) begin // si nrst_i es 0 (activo), resetea el registro a 0
			aux <= 0;
		end else begin
			aux <= y_o;
		end
	end

endmodule

AC2/labs/lab2/tb_accum_nbits.sv
module tb_adder_nbits;

    // Signal declaration
    parameter WIDTH = 16;
    parameter TESTSUM = 16;
    logic [WIDTH-1:0] x, y;
    logic [WIDTH:0] tmp;
    logic clk, rst;
    integer i;

    initial begin
        
    end

    // Instance of the accumulator under test
    accum_nbits #(.WIDTH(WIDTH)) accumulator (
      .clk_i(clk),
      .nrst_i(rst),
      .x_i(x),
      .y_o(y)
    );

    // Basic test for all the input combinations
    task basic_functional_testing();
        $display(" ------------------------------------------------");
        $display(" Basic test ");
        $display(" ------------------------------------------------");

        clk = 1; rst = 0; x = 0;
        #500 clk = 0; rst = 1;
        #500
        for (i = 0; i < TESTSUM; i++) begin
            clk = 1;
            x = i[WIDTH-1:0];
            tmp = tmp + i[WIDTH:0];
            #500 clk = 0;
            #500 assert (y[WIDTH-1:0] == tmp[WIDTH-1:0])
                 $display("(%0d) x=%d -> y=%d\n",$time,x,y);
                 else $error("ERROR! (%0d) x=%d -> y=%d\n",$time,x,y);
        end
    endtask

    // Main execution flow of the testbench
    initial begin 
        // wavefrom generation
        $dumpfile("waveform.vcd");
        $dumpvars();

        // Functionality testing of the 
        basic_functional_testing();
        $finish();
    end
                 
endmodule

AC2/labs/lab2/waveform.vcd
$version Generated by VerilatedVcd $end
$timescale 1ps $end
 $scope module TOP $end
  $scope module tb_adder_nbits $end
   $var wire 32 <! WIDTH [31:0] $end
   $var wire 32 <! TESTSUM [31:0] $end
   $var wire 16 # x [15:0] $end
   $var wire 16 8 y [15:0] $end
   $var wire 17 $ tmp [16:0] $end
   $var wire 1 % clk $end
   $var wire 1 & rst $end
   $var wire 32 ' i [31:0] $end
   $scope module accumulator $end
    $var wire 32 <! WIDTH [31:0] $end
    $var wire 1 % clk_i $end
    $var wire 1 & nrst_i $end
    $var wire 16 # x_i [15:0] $end
    $var wire 16 8 y_o [15:0] $end
    $var wire 16 +! aux [15:0] $end
    $scope module almendras3 $end
     $var wire 32 <! WIDTH [31:0] $end
     $var wire 16 # x_i [15:0] $end
     $var wire 16 +! y_i [15:0] $end
     $var wire 1 =! c_i $end
     $var wire 16 8 s_o [15:0] $end
     $var wire 1 9 c_o $end
     $var wire 17 : adder [16:0] $end
     $scope module genblk1[0] $end
      $scope module almendras2 $end
       $var wire 1 ( x_i $end
       $var wire 1 ,! y_i $end
       $var wire 1 =! c_i $end
       $var wire 1 ; s_o $end
       $var wire 1 < c_o $end
       $var wire 1 = a_int $end
       $var wire 1 =! b_int $end
       $var wire 1 > d_int $end
      $upscope $end
     $upscope $end
     $scope module genblk1[10] $end
      $scope module almendras2 $end
       $var wire 1 ) x_i $end
       $var wire 1 -! y_i $end
       $var wire 1 ? c_i $end
       $var wire 1 @ s_o $end
       $var wire 1 A c_o $end
       $var wire 1 B a_int $end
       $var wire 1 C b_int $end
       $var wire 1 D d_int $end
      $upscope $end
     $upscope $end
     $scope module genblk1[11] $end
      $scope module almendras2 $end
       $var wire 1 * x_i $end
       $var wire 1 .! y_i $end
       $var wire 1 A c_i $end
       $var wire 1 E s_o $end
       $var wire 1 F c_o $end
       $var wire 1 G a_int $end
       $var wire 1 H b_int $end
       $var wire 1 I d_int $end
      $upscope $end
     $upscope $end
     $scope module genblk1[12] $end
      $scope module almendras2 $end
       $var wire 1 + x_i $end
       $var wire 1 /! y_i $end
       $var wire 1 F c_i $end
       $var wire 1 J s_o $end
       $var wire 1 K c_o $end
       $var wire 1 L a_int $end
       $var wire 1 M b_int $end
       $var wire 1 N d_int $end
      $upscope $end
     $upscope $end
     $scope module genblk1[13] $end
      $scope module almendras2 $end
       $var wire 1 , x_i $end
       $var wire 1 0! y_i $end
       $var wire 1 K c_i $end
       $var wire 1 O s_o $end
       $var wire 1 P c_o $end
       $var wire 1 Q a_int $end
       $var wire 1 R b_int $end
       $var wire 1 S d_int $end
      $upscope $end
     $upscope $end
     $scope module genblk1[14] $end
      $scope module almendras2 $end
       $var wire 1 - x_i $end
       $var wire 1 1! y_i $end
       $var wire 1 P c_i $end
       $var wire 1 T s_o $end
       $var wire 1 U c_o $end
       $var wire 1 V a_int $end
       $var wire 1 W b_int $end
       $var wire 1 X d_int $end
      $upscope $end
     $upscope $end
     $scope module genblk1[15] $end
      $scope module almendras2 $end
       $var wire 1 . x_i $end
       $var wire 1 2! y_i $end
       $var wire 1 U c_i $end
       $var wire 1 Y s_o $end
       $var wire 1 9 c_o $end
       $var wire 1 Z a_int $end
       $var wire 1 [ b_int $end
       $var wire 1 \ d_int $end
      $upscope $end
     $upscope $end
     $scope module genblk1[1] $end
      $scope module almendras2 $end
       $var wire 1 / x_i $end
       $var wire 1 3! y_i $end
       $var wire 1 < c_i $end
       $var wire 1 ] s_o $end
       $var wire 1 ^ c_o $end
       $var wire 1 _ a_int $end
       $var wire 1 ` b_int $end
       $var wire 1 a d_int $end
      $upscope $end
     $upscope $end
     $scope module genblk1[2] $end
      $scope module almendras2 $end
       $var wire 1 0 x_i $end
       $var wire 1 4! y_i $end
       $var wire 1 ^ c_i $end
       $var wire 1 b s_o $end
       $var wire 1 c c_o $end
       $var wire 1 d a_int $end
       $var wire 1 e b_int $end
       $var wire 1 f d_int $end
      $upscope $end
     $upscope $end
     $scope module genblk1[3] $end
      $scope module almendras2 $end
       $var wire 1 1 x_i $end
       $var wire 1 5! y_i $end
       $var wire 1 c c_i $end
       $var wire 1 g s_o $end
       $var wire 1 h c_o $end
       $var wire 1 i a_int $end
       $var wire 1 j b_int $end
       $var wire 1 k d_int $end
      $upscope $end
     $upscope $end
     $scope module genblk1[4] $end
      $scope module almendras2 $end
       $var wire 1 2 x_i $end
       $var wire 1 6! y_i $end
       $var wire 1 h c_i $end
       $var wire 1 l s_o $end
       $var wire 1 m c_o $end
       $var wire 1 n a_int $end
       $var wire 1 o b_int $end
       $var wire 1 p d_int $end
      $upscope $end
     $upscope $end
     $scope module genblk1[5] $end
      $scope module almendras2 $end
       $var wire 1 3 x_i $end
       $var wire 1 7! y_i $end
       $var wire 1 m c_i $end
       $var wire 1 q s_o $end
       $var wire 1 r c_o $end
       $var wire 1 s a_int $end
       $var wire 1 t b_int $end
       $var wire 1 u d_int $end
      $upscope $end
     $upscope $end
     $scope module genblk1[6] $end
      $scope module almendras2 $end
       $var wire 1 4 x_i $end
       $var wire 1 8! y_i $end
       $var wire 1 r c_i $end
       $var wire 1 v s_o $end
       $var wire 1 w c_o $end
       $var wire 1 x a_int $end
       $var wire 1 y b_int $end
       $var wire 1 z d_int $end
      $upscope $end
     $upscope $end
     $scope module genblk1[7] $end
      $scope module almendras2 $end
       $var wire 1 5 x_i $end
       $var wire 1 9! y_i $end
       $var wire 1 w c_i $end
       $var wire 1 { s_o $end
       $var wire 1 | c_o $end
       $var wire 1 } a_int $end
       $var wire 1 ~ b_int $end
       $var wire 1 !! d_int $end
      $upscope $end
     $upscope $end
     $scope module genblk1[8] $end
      $scope module almendras2 $end
       $var wire 1 6 x_i $end
       $var wire 1 :! y_i $end
       $var wire 1 | c_i $end
       $var wire 1 "! s_o $end
       $var wire 1 #! c_o $end
       $var wire 1 $! a_int $end
       $var wire 1 %! b_int $end
       $var wire 1 &! d_int $end
      $upscope $end
     $upscope $end
     $scope module genblk1[9] $end
      $scope module almendras2 $end
       $var wire 1 7 x_i $end
       $var wire 1 ;! y_i $end
       $var wire 1 #! c_i $end
       $var wire 1 '! s_o $end
       $var wire 1 ? c_o $end
       $var wire 1 (! a_int $end
       $var wire 1 )! b_int $end
       $var wire 1 *! d_int $end
      $upscope $end
     $upscope $end
    $upscope $end
   $upscope $end
  $upscope $end
 $upscope $end
$enddefinitions $end


#0
b0000000000000000 #
b00000000000000000 $
1%
0&
b00000000000000000000000000000000 '
0(
0)
0*
0+
0,
0-
0.
0/
00
01
02
03
04
05
06
07
b0000000000000000 8
09
b00000000000000000 :
0;
0<
0=
0>
0?
0@
0A
0B
0C
0D
0E
0F
0G
0H
0I
0J
0K
0L
0M
0N
0O
0P
0Q
0R
0S
0T
0U
0V
0W
0X
0Y
0Z
0[
0\
0]
0^
0_
0`
0a
0b
0c
0d
0e
0f
0g
0h
0i
0j
0k
0l
0m
0n
0o
0p
0q
0r
0s
0t
0u
0v
0w
0x
0y
0z
0{
0|
0}
0~
0!!
0"!
0#!
0$!
0%!
0&!
0'!
0(!
0)!
0*!
b0000000000000000 +!
0,!
0-!
0.!
0/!
00!
01!
02!
03!
04!
05!
06!
07!
08!
09!
0:!
0;!
b00000000000000000000000000010000 <!
0=!
#50
#100
#150
#200
#250
#300
#350
#400
#450
#500
0%
1&
#550
#600
#650
#700
#750
#800
#850
#900
#950
#1000
1%
#1050
#1100
#1150
#1200
#1250
#1300
#1350
#1400
#1450
#1500
0%
#1550
#1600
#1650
#1700
#1750
#1800
#1850
#1900
#1950
#2000
b0000000000000001 #
b00000000000000001 $
1%
b00000000000000000000000000000001 '
1(
#2050
#2100
1=
#2150
#2200
b0000000000000001 8
1;
#2250
#2300
#2350
#2400
#2450
#2500
0%
#2550
#2600
#2650
#2700
#2750
#2800
#2850
#2900
#2950
#3000
b0000000000000010 #
b00000000000000011 $
1%
b00000000000000000000000000000010 '
0(
1/
b0000000000000001 +!
1,!
#3050
#3100
1_
#3150
#3200
b0000000000000011 8
1]
#3250
#3300
#3350
#3400
#3450
#3500
0%
#3550
#3600
#3650
#3700
#3750
#3800
#3850
#3900
#3950
#4000
b0000000000000011 #
b00000000000000110 $
1%
b00000000000000000000000000000011 '
1(
b0000000000000011 +!
13!
#4050
1>
1a
#4100
0=
0_
#4150
b00000000000000110 :
1<
1^
#4200
b0000000000000000 8
0;
0]
#4250
b0000000000000110 8
1]
1b
#4300
#4350
#4400
#4450
#4500
0%
#4550
#4600
#4650
#4700
#4750
#4800
#4850
#4900
#4950
#5000
b0000000000000100 #
b00000000000001010 $
1%
b00000000000000000000000000000100 '
0(
0/
10
b0000000000000110 +!
0,!
14!
#5050
0>
0a
1f
#5100
1_
#5150
b00000000000001000 :
0<
0^
1`
1c
#5200
b0000000000000100 8
0]
0`
#5250
b0000000000001010 8
b00000000000001100 :
1]
1^
0b
1g
#5300
b00000000000001000 :
0^
#5350
b0000000000001110 8
1b
#5400
b0000000000001010 8
0b
#5450
#5500
0%
#5550
#5600
#5650
#5700
#5750
#5800
#5850
#5900
#5950
#6000
b0000000000000101 #
b00000000000001111 $
1%
b00000000000000000000000000000101 '
1(
b0000000000001010 +!
04!
15!
#6050
0f
#6100
1=
1d
1i
#6150
b00000000000000000 :
0c
1j
#6200
b0000000000000111 8
1;
1b
0g
0j
#6250
b0000000000001111 8
b00000000000010000 :
1g
1h
#6300
b00000000000000000 :
0h
#6350
b0000000000011111 8
1l
#6400
b0000000000001111 8
0l
#6450
#6500
0%
#6550
#6600
#6650
#6700
#6750
#6800
#6850
#6900
#6950
#7000
b0000000000000110 #
b00000000000010101 $
1%
b00000000000000000000000000000110 '
0(
1/
b0000000000001111 +!
1,!
14!
#7050
1a
1f
#7100
0_
0d
#7150
b00000000000001100 :
1^
1c
#7200
b0000000000001001 8
0]
0b
1j
#7250
b0000000000000101 8
1b
0g
#7300
b00000000000011100 :
1h
#7350
#7400
b0000000000010101 8
1l
#7450
#7500
0%
#7550
#7600
#7650
#7700
#7750
#7800
#7850
#7900
#7950
#8000
b0000000000000111 #
b00000000000011100 $
1%
b00000000000000000000000000000111 '
1(
b0000000000010101 +!
03!
05!
16!
#8050
1>
0a
#8100
0=
1_
0i
1n
#8150
b00000000000011010 :
1<
0^
0j
1o
#8200
b0000000000001110 8
0;
1]
1`
1g
0l
#8250
b0000000000001000 8
b00000000000101010 :
0]
0b
0h
1m
#8300
b00000000000101110 :
1^
0o
#8350
b0000000000111000 8
1l
1q
#8400
b0000000000111100 8
b00000000000001110 :
1b
0m
#8450
#8500
0%
b0000000000011100 8
0q
#8550
#8600
#8650
#8700
#8750
#8800
#8850
#8900
#8950
#9000
b0000000000001000 #
b00000000000100100 $
1%
b00000000000000000000000000001000 '
0(
0/
00
11
b0000000000011100 +!
0,!
15!
#9050
0>
0f
1k
#9100
0_
1d
#9150
b00000000000010100 :
0<
0`
0c
1e
1h
#9200
b0000000000011010 8
1]
0b
1o
#9250
b0000000000000000 8
b00000000000011000 :
0]
0^
1c
0g
0l
#9300
b00000000000111000 :
0e
1m
#9350
b0000000000001100 8
1b
1g
#9400
b0000000000101100 8
b00000000000110000 :
0c
1q
#9450
#9500
0%
b0000000000100100 8
0g
#9550
#9600
#9650
#9700
#9750
#9800
#9850
#9900
#9950
#10000
b0000000000001001 #
b00000000000101101 $
1%
b00000000000000000000000000001001 '
1(
b0000000000100100 +!
05!
06!
17!
#10050
0k
#10100
1=
1i
0n
1s
#10150
b00000000000100000 :
0h
0o
1t
#10200
b0000000000011101 8
1;
1g
1l
0q
#10250
b0000000000001101 8
b00000000001000000 :
0l
0m
1r
#10300
0t
#10350
b0000000001101101 8
1q
1v
#10400
b00000000000000000 :
0r
#10450
#10500
0%
b0000000000101101 8
0v
#10550
#10600
#10650
#10700
#10750
#10800
#10850
#10900
#10950
#11000
b0000000000001010 #
b00000000000110111 $
1%
b00000000000000000000000000001010 '
0(
1/
b0000000000101101 +!
1,!
15!
#11050
1k
#11100
1_
0i
#11150
b00000000000010000 :
1h
#11200
b0000000000100111 8
1]
0g
#11250
b0000000000110111 8
1l
#11300
#11350
#11400
#11450
#11500
0%
#11550
#11600
#11650
#11700
#11750
#11800
#11850
#11900
#11950
#12000
b0000000000001011 #
b00000000001000010 $
1%
b00000000000000000000000000001011 '
1(
b0000000000110111 +!
13!
05!
16!
#12050
1>
1a
0k
#12100
0=
0_
1i
1n
#12150
b00000000000000110 :
1<
1^
0h
1o
#12200
b0000000000101100 8
0;
0]
1e
1g
0l
0o
#12250
b0000000000111010 8
b00000000000100110 :
1]
0b
1l
1m
#12300
b00000000000001110 :
1c
0m
1t
#12350
b0000000000011010 8
1j
0q
0t
#12400
b0000000000110010 8
b00000000001001110 :
0g
1q
1r
#12450
b00000000000011110 :
1h
0r
#12500
0%
b0000000001110010 8
1o
1v
#12550
b0000000000100010 8
0l
0v
#12600
b00000000000111110 :
1m
#12650
1t
#12700
b0000000000000010 8
0q
#12750
b00000000001111110 :
1r
#12800
#12850
b0000000001000010 8
1v
#12900
#12950
#13000
b0000000000001100 #
b00000000001001110 $
1%
b00000000000000000000000000001100 '
0(
0/
10
b0000000001000010 +!
0,!
04!
06!
07!
18!
#13050
0>
0a
#13100
1_
0n
0s
1x
#13150
b00000000001111000 :
0<
0^
1`
0o
0t
1y
#13200
b0000000000110000 8
0]
0`
0e
1l
1q
0v
#13250
b0000000000110110 8
b00000000010011100 :
1]
1^
1b
0m
0r
1w
#13300
b00000000010010000 :
0^
0c
1e
0y
#13350
b0000000011010010 8
0b
0e
0j
0q
1v
1{
#13400
b0000000011011110 8
b00000000000011000 :
1b
1c
1g
0w
#13450
b00000000000000000 :
0c
0h
1j
#13500
0%
b0000000001010110 8
0g
0j
0{
#13550
b0000000001001110 8
b00000000000010000 :
1g
1h
0l
#13600
b00000000000000000 :
0h
#13650
b0000000001011110 8
1l
#13700
b0000000001001110 8
0l
#13750
#13800
#13850
#13900
#13950
#14000
b0000000000001101 #
b00000000001011011 $
1%
b00000000000000000000000000001101 '
1(
b0000000001001110 +!
14!
15!
#14050
1f
1k
#14100
1=
0d
0i
#14150
b00000000000011000 :
1c
1h
#14200
b0000000001000011 8
1;
0b
0g
#14250
b0000000001011011 8
1g
1l
#14300
#14350
#14400
#14450
#14500
0%
#14550
#14600
#14650
#14700
#14750
#14800
#14850
#14900
#14950
#15000
b0000000000001110 #
b00000000001101001 $
1%
b00000000000000000000000000001110 '
0(
1/
b0000000001011011 +!
1,!
04!
16!
#15050
1a
0f
#15100
0_
1d
1n
#15150
b00000000000010100 :
1^
0c
1o
#15200
b0000000001001101 8
0]
1b
1e
0l
#15250
b0000000001000001 8
b00000000000110100 :
0b
0g
1m
#15300
b00000000000111100 :
1c
#15350
b0000000001100001 8
1q
#15400
b0000000001101001 8
1g
#15450
#15500
0%
#15550
#15600
#15650
#15700
#15750
#15800
#15850
#15900
#15950
#16000
b0000000000001111 #
b00000000001111000 $
1%
b00000000000000000000000000001111 '
1(
b0000000001101001 +!
03!
06!
17!
#16050
1>
0a
#16100
0=
1_
0n
1s
#16150
b00000000000111010 :
1<
0^
0o
1t
#16200
b0000000001011010 8
0;
1]
1`
0e
1l
0q
#16250
b0000000001011100 8
b00000000001011010 :
0]
1b
0m
1r
#16300
b00000000001010110 :
1^
0c
0t
1y
#16350
b0000000000111100 8
1e
1q
0v
#16400
b0000000000110000 8
b00000000010010110 :
0b
0g
0r
1w
#16450
b00000000010011110 :
1c
0y
#16500
0%
b0000000011110000 8
1v
1{
#16550
b0000000011111000 8
b00000000000011110 :
1g
0w
#16600
#16650
b0000000001111000 8
0{
#16700
#16750
#16800
#16850
#16900
#16950
#17000
b00000000000000000000000000010000 '
