AC2/labs/lab1/full_adder.sv
module full_adder (
	input logic x_i,
	input logic y_i,
	input logic c_i,

	output logic s_o,
	output logic c_o
);

// Declaracion de señales intermedias
	logic A;
	logic B;
	logic D;

// Arquitectura de un full adder
	assign #(100) A = x_i ^ y_i;
	assign #(50) B = A & c_i;
	assign #(50) D = x_i & y_i;
	assign #(100) c_o = B | D;
	assign #(100) s_o = A ^ c_i;

endmodule

AC2/labs/lab1/tb_full_adder.sv
module full_adder_tb;

    // Signal declaration
    reg clk;
    reg x,y,cin;
    wire sum,carry;
    integer i,j,k;

    initial begin
        
    end

    // Instance of the full_adder under test
    full_adder full_adder_inst(
        .x_i(x),
        .y_i(y),
        .c_i(cin),
        .s_o(sum),
        .c_o(carry));

    // Basic test for all the input combinations
    task basic_functional_testing();
        $display(" ------------------------------------------------");
        $display(" Basic test ");
        $display(" ------------------------------------------------");

        clk = 1; x = 0; y = 0; cin = 0;
        #500 clk = 0;
        #500
        for (i=0;i<2;i++) begin
            for (j=0;j<2;j++) begin
                for (k=0;k<2;k++) begin
                    clk = 1; x = i[0]; y = j[0]; cin = k[0];
                    #500 clk = 0;
                    #500 assert ((i+j+k) == (integer'(sum)+2*integer'(carry))) 
                         $display("(%0d) x=%b y=%b Cin=%b -> Sum=%b Cout=%b\n",$time,x,y,cin,sum,carry);
                         else $error("ERROR! (%0d) x=%b y=%b Cin=%b -> Sum=%b Cout=%b\n",$time,x,y,cin,sum,carry);

                end
            end
        end
    endtask

    // Transition test for evaluating the different delays
    task transition_test(
        input logic a0,
        input logic b0,
        input logic c0,
        input logic a1,
        input logic b1,
        input logic c1);

        $display(" ------------------------------------------------");
        $display(" Transition test: x=%b->%b y=%b->%b Cin=%b->%b",a0,a1,b0,b1,c0,c1);
        $display(" ------------------------------------------------");


        clk = 1; x = a0; y = b0; cin = c0;
        #500 clk = 0;
        #500 $display("(%0d) FROM: x=%b y=%b Cin=%b -> Sum=%b Cout=%b\n",$time,x,y,cin,sum,carry);
        clk = 1; x = a1; y = b1; cin = c1;
        #500 clk = 0;
        #500 $display("(%0d) TO: x=%b y=%b Cin=%b -> Sum=%b Cout=%b\n",$time,x,y,cin,sum,carry);
    endtask

    // Main execution flow of the testbench
    initial begin 
        // wavefrom generation
        $dumpfile("waveform.vcd");
        $dumpvars();

        // Functionality testing of the 
        basic_functional_testing();
        transition_test(    
            1'b0,1'b0,1'b0,  // from (x,y,c)
            1'b1,1'b1,1'b1); // to   (x,y,c)
        $finish();
    end
                 
endmodule

AC2/labs/lab1/waveform.vcd
$version Generated by VerilatedVcd $end
$timescale 1ps $end
 $scope module TOP $end
  $scope module full_adder_tb $end
   $var wire 1 # clk $end
   $var wire 1 $ x $end
   $var wire 1 % y $end
   $var wire 1 & cin $end
   $var wire 1 * sum $end
   $var wire 1 + carry $end
   $var wire 32 ' i [31:0] $end
   $var wire 32 ( j [31:0] $end
   $var wire 32 ) k [31:0] $end
   $scope module full_adder_inst $end
    $var wire 1 $ x_i $end
    $var wire 1 % y_i $end
    $var wire 1 & c_i $end
    $var wire 1 * s_o $end
    $var wire 1 + c_o $end
    $var wire 1 , A $end
    $var wire 1 - B $end
    $var wire 1 . D $end
   $upscope $end
  $upscope $end
 $upscope $end
$enddefinitions $end


#0
1#
0$
0%
0&
b00000000000000000000000000000000 '
b00000000000000000000000000000000 (
b00000000000000000000000000000000 )
0*
0+
0,
0-
0.
#50
#100
#150
#200
#250
#300
#350
#400
#450
#500
0#
#550
#600
#650
#700
#750
#800
#850
#900
#950
#1000
1#
#1050
#1100
#1150
#1200
#1250
#1300
#1350
#1400
#1450
#1500
0#
#1550
#1600
#1650
#1700
#1750
#1800
#1850
#1900
#1950
#2000
1#
1&
b00000000000000000000000000000001 )
#2050
#2100
1*
#2150
#2200
#2250
#2300
#2350
#2400
#2450
#2500
0#
#2550
#2600
#2650
#2700
#2750
#2800
#2850
#2900
#2950
#3000
1#
1%
0&
b00000000000000000000000000000001 (
b00000000000000000000000000000010 )
#3050
#3100
0*
1,
#3150
#3200
1*
#3250
#3300
#3350
#3400
#3450
#3500
0#
#3550
#3600
#3650
#3700
#3750
#3800
#3850
#3900
#3950
#4000
1#
1&
b00000000000000000000000000000001 )
#4050
1-
#4100
0*
#4150
1+
#4200
#4250
#4300
#4350
#4400
#4450
#4500
0#
#4550
#4600
#4650
#4700
#4750
#4800
#4850
#4900
#4950
#5000
1#
1$
0%
0&
b00000000000000000000000000000001 '
b00000000000000000000000000000010 (
b00000000000000000000000000000010 )
#5050
0-
#5100
1*
#5150
0+
#5200
#5250
#5300
#5350
#5400
#5450
#5500
0#
#5550
#5600
#5650
#5700
#5750
#5800
#5850
#5900
#5950
#6000
1#
1&
b00000000000000000000000000000001 )
#6050
1-
#6100
0*
#6150
1+
#6200
#6250
#6300
#6350
#6400
#6450
#6500
0#
#6550
#6600
#6650
#6700
#6750
#6800
#6850
#6900
#6950
#7000
1#
1%
0&
b00000000000000000000000000000001 (
b00000000000000000000000000000010 )
#7050
0-
1.
#7100
1*
0,
#7150
#7200
0*
#7250
#7300
#7350
#7400
#7450
#7500
0#
#7550
#7600
#7650
#7700
#7750
#7800
#7850
#7900
#7950
#8000
1#
1&
b00000000000000000000000000000001 )
#8050
#8100
1*
#8150
#8200
#8250
#8300
#8350
#8400
#8450
#8500
0#
#8550
#8600
#8650
#8700
#8750
#8800
#8850
#8900
#8950
#9000
1#
0$
0%
0&
b00000000000000000000000000000010 '
b00000000000000000000000000000010 (
b00000000000000000000000000000010 )
#9050
0.
#9100
0*
#9150
0+
#9200
#9250
#9300
#9350
#9400
#9450
#9500
0#
#9550
#9600
#9650
#9700
#9750
#9800
#9850
#9900
#9950
#10000
1#
1$
1%
1&
#10050
1.
#10100
1*
#10150
1+
