AC2/labs/lab1/full_adder.sv
module full_adder (
	input logic x_i,
	input logic y_i,
	input logic c_i,

	output logic s_o,
	output logic c_o
);

// Declaracion de señales intermedias
	logic A;
	logic B;
	logic D;

// Arquitectura de un full adder
	assign #(100) A = x_i ^ y_i;
	assign #(50) B = A & c_i;
	assign #(50) D = x_i & y_i;
	assign #(100) c_o = B | D;
	assign #(100) s_o = A ^ c_i;

endmodule

AC2/labs/lab1/tb_full_adder.sv
module full_adder_tb;

    // Signal declaration
    reg clk;
    reg x,y,cin;
    wire sum,carry;
    integer i,j,k;

    initial begin
        
    end

    // Instance of the full_adder under test
    full_adder full_adder_inst(
        .x_i(x),
        .y_i(y),
        .c_i(cin),
        .s_o(sum),
        .c_o(carry));

    // Basic test for all the input combinations
    task basic_functional_testing();
        $display(" ------------------------------------------------");
        $display(" Basic test ");
        $display(" ------------------------------------------------");

        clk = 1; x = 0; y = 0; cin = 0;
        #500 clk = 0;
        #500
        for (i=0;i<2;i++) begin
            for (j=0;j<2;j++) begin
                for (k=0;k<2;k++) begin
                    clk = 1; x = i[0]; y = j[0]; cin = k[0];
                    #500 clk = 0;
                    #500 assert ((i+j+k) == (integer'(sum)+2*integer'(carry))) 
                         $display("(%0d) x=%b y=%b Cin=%b -> Sum=%b Cout=%b\n",$time,x,y,cin,sum,carry);
                         else $error("ERROR! (%0d) x=%b y=%b Cin=%b -> Sum=%b Cout=%b\n",$time,x,y,cin,sum,carry);

                end
            end
        end
    endtask

    // Transition test for evaluating the different delays
    task transition_test(
        input logic a0,
        input logic b0,
        input logic c0,
        input logic a1,
        input logic b1,
        input logic c1);

        $display(" ------------------------------------------------");
        $display(" Transition test: x=%b->%b y=%b->%b Cin=%b->%b",a0,a1,b0,b1,c0,c1);
        $display(" ------------------------------------------------");


        clk = 1; x = a0; y = b0; cin = c0;
        #500 clk = 0;
        #500 $display("(%0d) FROM: x=%b y=%b Cin=%b -> Sum=%b Cout=%b\n",$time,x,y,cin,sum,carry);
        clk = 1; x = a1; y = b1; cin = c1;
        #500 clk = 0;
        #500 $display("(%0d) TO: x=%b y=%b Cin=%b -> Sum=%b Cout=%b\n",$time,x,y,cin,sum,carry);
    endtask

// En esta funcion se prueban maximos y minimos, ahora estan puestos los minimos porque era el ultimo ejercicio pero 
// simplemente seria cambiar los vectores de entrada y ya. Respecto al ejercicio 2, se podia hacer manual o con codigo
// y nosotros hicimos ambas, para el codigo lo unico que cambia es hacer el basic test, añadiendo un clock mas por 
// iteracion y haciendo asignacion y display de 0 a x, y, c.

    task custom_testing();
	$display(" ------------------------------------------------");
        $display(" Basic test ");
        $display(" ------------------------------------------------");

        clk = 1; x = 0; y = 0; cin = 0;
        #500 clk = 0;
        #500 clk = 1; x = 0; y = 0; cin = 0;
        #500 clk = 0;
        #500 
	     $display("(%0d) x=%b y=%b Cin=%b -> Sum=%b Cout=%b\n",$time,x,y,cin,sum,carry);
	     clk = 1; x = 0; y = 0; cin = 1;
	 #500 clk = 0;
	 #500 $display("(%0d) x=%b y=%b Cin=%b -> Sum=%b Cout=%b\n",$time,x,y,cin,sum,carry);
    endtask

    // Main execution flow of the testbench
    initial begin 
        // wavefrom generation
        $dumpfile("waveform.vcd");
        $dumpvars();

        // Functionality testing of the 
        // basic_functional_testing();
	custom_testing();
        transition_test(    
            1'b0,1'b0,1'b0,  // from (x,y,c)
            1'b1,1'b1,1'b1); // to   (x,y,c)
        $finish();
    end
                 
endmodule

AC2/labs/lab1/waveform.vcd
$version Generated by VerilatedVcd $end
$timescale 1ps $end
 $scope module TOP $end
  $scope module full_adder_tb $end
   $var wire 1 ( clk $end
   $var wire 1 ) x $end
   $var wire 1 * y $end
   $var wire 1 + cin $end
   $var wire 1 # sum $end
   $var wire 1 $ carry $end
   $var wire 32 , i [31:0] $end
   $var wire 32 - j [31:0] $end
   $var wire 32 . k [31:0] $end
   $scope module full_adder_inst $end
    $var wire 1 ) x_i $end
    $var wire 1 * y_i $end
    $var wire 1 + c_i $end
    $var wire 1 # s_o $end
    $var wire 1 $ c_o $end
    $var wire 1 % A $end
    $var wire 1 & B $end
    $var wire 1 ' D $end
   $upscope $end
  $upscope $end
 $upscope $end
$enddefinitions $end


#0
0#
0$
0%
0&
0'
1(
0)
0*
0+
b00000000000000000000000000000000 ,
b00000000000000000000000000000000 -
b00000000000000000000000000000000 .
#50
#100
#150
#200
#250
#300
#350
#400
#450
#500
0(
#550
#600
#650
#700
#750
#800
#850
#900
#950
#1000
1(
#1050
#1100
#1150
#1200
#1250
#1300
#1350
#1400
#1450
#1500
0(
#1550
#1600
#1650
#1700
#1750
#1800
#1850
#1900
#1950
#2000
1(
1+
#2050
#2100
1#
#2150
#2200
#2250
#2300
#2350
#2400
#2450
#2500
0(
#2550
#2600
#2650
#2700
#2750
#2800
#2850
#2900
#2950
#3000
1(
0+
#3050
#3100
0#
#3150
#3200
#3250
#3300
#3350
#3400
#3450
#3500
0(
#3550
#3600
#3650
#3700
#3750
#3800
#3850
#3900
#3950
#4000
1(
1)
1*
1+
#4050
1'
#4100
1#
#4150
1$
